memu/__init__.py
memu/_core.abi3.so
memu/_core.pyi
memu/app/__init__.py
memu/app/crud.py
memu/app/memorize.py
memu/app/patch.py
memu/app/retrieve.py
memu/app/service.py
memu/app/settings.py
memu/blob/__init__.py
memu/blob/local_fs.py
memu/database/__init__.py
memu/database/factory.py
memu/database/inmemory/__init__.py
memu/database/inmemory/models.py
memu/database/inmemory/repo.py
memu/database/inmemory/repositories/__init__.py
memu/database/inmemory/repositories/category_item_repo.py
memu/database/inmemory/repositories/filter.py
memu/database/inmemory/repositories/memory_category_repo.py
memu/database/inmemory/repositories/memory_item_repo.py
memu/database/inmemory/repositories/resource_repo.py
memu/database/inmemory/state.py
memu/database/inmemory/vector.py
memu/database/interfaces.py
memu/database/models.py
memu/database/postgres/__init__.py
memu/database/postgres/migration.py
memu/database/postgres/migrations/__init__.py
memu/database/postgres/migrations/env.py
memu/database/postgres/models.py
memu/database/postgres/postgres.py
memu/database/postgres/repositories/__init__.py
memu/database/postgres/repositories/base.py
memu/database/postgres/repositories/category_item_repo.py
memu/database/postgres/repositories/memory_category_repo.py
memu/database/postgres/repositories/memory_item_repo.py
memu/database/postgres/repositories/resource_repo.py
memu/database/postgres/schema.py
memu/database/postgres/session.py
memu/database/repositories/__init__.py
memu/database/repositories/category_item.py
memu/database/repositories/memory_category.py
memu/database/repositories/memory_item.py
memu/database/repositories/resource.py
memu/database/sqlite/__init__.py
memu/database/sqlite/models.py
memu/database/sqlite/repositories/__init__.py
memu/database/sqlite/repositories/base.py
memu/database/sqlite/repositories/category_item_repo.py
memu/database/sqlite/repositories/memory_category_repo.py
memu/database/sqlite/repositories/memory_item_repo.py
memu_py-1.3.0.dist-info/METADATA
memu_py-1.3.0.dist-info/WHEEL
memu_py-1.3.0.dist-info/entry_points.txt
memu_py-1.3.0.dist-info/licenses/LICENSE.txt
memu_py-1.3.0.dist-info/RECORD
