Metadata-Version: 2.4
Name: memu-py
Version: 1.3.0
Classifier: Development Status :: 4 - Beta
Classifier: Intended Audience :: Developers
Classifier: Operating System :: OS Independent
Classifier: Programming Language :: Python :: 3
Classifier: Programming Language :: Python :: 3.13
Requires-Dist: defusedxml>=0.7.1
Requires-Dist: httpx>=0.28.1
Requires-Dist: numpy>=2.3.4
Requires-Dist: openai>=2.8.0
Requires-Dist: pydantic>=2.12.4
Requires-Dist: sqlmodel>=0.0.27
Requires-Dist: alembic>=1.14.0
Requires-Dist: pendulum>=3.1.0
Requires-Dist: langchain-core>=1.2.7
Requires-Dist: lazyllm>=0.7.3
Requires-Dist: claude-agent-sdk>=0.1.24 ; extra == 'claude'
Requires-Dist: langgraph>=0.0.10 ; extra == 'langgraph'
Requires-Dist: langchain-core>=0.1.0 ; extra == 'langgraph'
Requires-Dist: pgvector>=0.3.4 ; extra == 'postgres'
Requires-Dist: sqlalchemy[postgresql-psycopgbinary]>=2.0.36 ; extra == 'postgres'
Provides-Extra: claude
Provides-Extra: langgraph
Provides-Extra: postgres
License-File: LICENSE.txt
Summary: AI Memory and Conversation Management Framework - Simple as mem0, Powerful as MemU
Keywords: ai,memory,conversation,llm,chatbot,agent
Author-email: MemU Team <contact@nevamind.ai>
Requires-Python: >=3.13
Project-URL: Bug Tracker, https://github.com/NevaMind-AI/MemU/issues
Project-URL: Documentation, https://github.com/NevaMind-AI/MemU#readme
Project-URL: Homepage, https://github.com/NevaMind-AI/MemU
